seqp/__init__.py
seqp/encoding.py
seqp/hdf5.py
seqp/iteration.py
seqp/memory.py
seqp/record.py
seqp/util.py
seqp/vocab.py
seqp/integration/__init__.py
seqp/integration/torch.py
seqp/integration/fairseq/__init__.py
seqp/integration/fairseq/dataset.py
seqp/integration/fairseq/dictionary.py
seqp/integration/fairseq/preprocess.py
seqp/integration/fairseq/task.py
seqp-0.1.dist-info/LICENSE
seqp-0.1.dist-info/METADATA
seqp-0.1.dist-info/WHEEL
seqp-0.1.dist-info/top_level.txt
seqp-0.1.dist-info/RECORD
